[
  {
    "number": 1,
    "path": "assets/Slika1Prica1.png",
    "name": "Pubertet"
  },
  {
    "number": 2,
    "path": "assets/Slika1Prica2.jpg",
    "name": "Obavljam ličnu higijenu"
  },
  {
    "number": 3,
    "path": "assets/Slika1Prica3.png",
    "name": "Bijes je"
  },
  {
    "number": 4,
    "path": "assets/Slika1Prica4.png",
    "name": "KADA SAM BIJESAN/UZNEMIREN"
  },
  {
    "number": 5,
    "path": "assets/Slika1Prica5.png",
    "name": "Biti tužan"
  },
  {
    "number": 6,
    "path": "assets/Slika1Prica6.png",
    "name": "Strah je"
  },
  {
    "number": 7,
    "path": "assets/Slika1Prica7.png",
    "name": "Moj novi razred"
  },
  {
    "number": 8,
    "path": "assets/Slika1Prica8.png",
    "name": "Dodirivanje intimnih djelova tijela i privatni prostor"
  },
  {
    "number": 9,
    "path": "assets/Slika1Prica9.jpg",
    "name": "Grudnjak"
  },
  {
    "number": 10,
    "path": "assets/Slika1Prica10.jpg",
    "name": "Menstruacija (Kako koristim uloške)"
  },
  {
    "number": 11,
    "path": "assets/Slika1Prica11.jpg",
    "name": "Pobjeđivanje i gubljenje"
  }
]
